sealpy/__init__.py
sealpy/cipher.py
sealpy/config.py
sealpy/read.py
sealpy/utilitis.py
seal_py-0.8.4.dist-info/METADATA
seal_py-0.8.4.dist-info/WHEEL
seal_py-0.8.4.dist-info/RECORD
